PackLab/__init__.py
PackLab/_version.py
PackLab/analytical/__init__.py
PackLab/analytical/distributions.py
PackLab/analytical/domain.py
PackLab/analytical/solver.py
PackLab/analytical.py
PackLab/binary/__init__.py
PackLab/binary/interface_domain.cp311-win_amd64.pyd
PackLab/binary/interface_domain.cp312-win_amd64.pyd
PackLab/binary/interface_radius_sampler.cp311-win_amd64.pyd
PackLab/binary/interface_radius_sampler.cp312-win_amd64.pyd
PackLab/binary/interface_result.cp311-win_amd64.pyd
PackLab/binary/interface_result.cp312-win_amd64.pyd
PackLab/binary/interface_rsa.cp311-win_amd64.pyd
PackLab/binary/interface_rsa.cp312-win_amd64.pyd
PackLab/binary/interface_statistics.cp311-win_amd64.pyd
PackLab/binary/interface_statistics.cp312-win_amd64.pyd
PackLab/binary/libdomain.a
PackLab/binary/libradius_sampler.a
PackLab/binary/libresult.a
PackLab/binary/librsa.a
PackLab/binary/libstatistics.a
PackLab/binary/libutils.a
PackLab/directories.py
PackLab/monte_carlo/__init__.py
PackLab/monte_carlo/results.py
PackLab/monte_carlo/simulator.py
PackLab/monte_carlo/utils.py
packlab-0.0.11.dist-info/METADATA
packlab-0.0.11.dist-info/WHEEL
packlab-0.0.11.dist-info/licenses/LICENSE
packlab-0.0.11.dist-info/RECORD
