Metadata-Version: 2.4
Name: PackLab
Version: 0.0.11
Summary: Random Sequential Addition (RSA) particle packing with a fast C++ core.
Keywords: rsa,packing,particles,spheres,simulation
Author-Email: Martin Poinsinet de Sivry-Houle <martin.poinsinet.de.sivry@gmail.com>
License-Expression: MIT
Classifier: Development Status :: 4 - Beta
Classifier: Programming Language :: Python
Classifier: Programming Language :: Python :: 3
Classifier: Programming Language :: Python :: 3 :: Only
Classifier: Programming Language :: Python :: 3.11
Classifier: Programming Language :: Python :: 3.12
Classifier: Programming Language :: Python :: 3.13
Classifier: Programming Language :: Python :: Implementation :: CPython
Classifier: Programming Language :: C++
Classifier: Operating System :: MacOS
Classifier: Operating System :: Microsoft :: Windows
Classifier: Operating System :: POSIX :: Linux
Classifier: Topic :: Scientific/Engineering
Project-URL: Homepage, https://github.com/MartinPdeS/PackLab
Project-URL: Repository, https://github.com/MartinPdeS/PackLab
Project-URL: Issues, https://github.com/MartinPdeS/PackLab/issues
Project-URL: Documentation, https://martinpdes.github.io/PackLab/docs/latest/index.html
Requires-Python: >=3.10
Requires-Dist: pydantic>=2.6.3
Requires-Dist: MPSPlots
Requires-Dist: numpy
Requires-Dist: TypedUnit
Requires-Dist: tabulate
Provides-Extra: testing
Requires-Dist: pytest>=0.6; extra == "testing"
Requires-Dist: pytest-cov>=2.0; extra == "testing"
Requires-Dist: pytest-json-report==1.5.0; extra == "testing"
Requires-Dist: flake8>=3.9; extra == "testing"
Requires-Dist: coverage==7.10.7; extra == "testing"
Provides-Extra: documentation
Requires-Dist: numpydoc==1.9.0; extra == "documentation"
Requires-Dist: sphinx>=5.1.1; extra == "documentation"
Requires-Dist: sphinx-gallery==0.19.0; extra == "documentation"
Requires-Dist: pydata-sphinx-theme==0.16.1; extra == "documentation"
Requires-Dist: sphinx-rtd-theme==3.0.2; extra == "documentation"
Provides-Extra: dev
Requires-Dist: flake==7.2.0; extra == "dev"
